manrododex/__init__.py
manrododex/__main__.py
manrododex/apiadapter.py
manrododex/downloader.py
manrododex/exceptions.py
manrododex/logger.py
manrododex/main.py
manrododex/manga.py
manrododex/manga_helpers.py
manrododex/mangadex_lang_codes.py
manrododex/system_helper.py
manrododex/CLI/__init__.py
manrododex/CLI/argparse.py
manrododex/CLI/downloading_args.py
manrododex/CLI/general_args.py
manrododex/CLI/required_args.py
manrododex-1.0.5.dist-info/LICENSE
manrododex-1.0.5.dist-info/METADATA
manrododex-1.0.5.dist-info/WHEEL
manrododex-1.0.5.dist-info/entry_points.txt
manrododex-1.0.5.dist-info/top_level.txt
manrododex-1.0.5.dist-info/RECORD
