Metadata-Version: 2.1
Name: manrododex
Version: 1.0.5
Summary: A manga downloader for mangadex
Home-page: https://github.com/Sydiepus/Manrododex
Author: Charbel Assaad
Author-email: sydiepus@gmail.com
License: MIT
Project-URL: Documentation, https://manrododex.readthedocs.io/en/latest/
Project-URL: Code, https://github.com/Sydiepus/Manrododex
Project-URL: Issue tracker, https://github.com/Sydiepus/Manrododex/issues
Keywords: mangadex,manga,downloader
Classifier: Development Status :: 4 - Beta
Classifier: Environment :: Console
Classifier: Intended Audience :: End Users/Desktop
Classifier: License :: OSI Approved :: MIT License
Classifier: Natural Language :: English
Classifier: Operating System :: OS Independent
Classifier: Programming Language :: Python :: 3 :: Only
Classifier: Programming Language :: Python :: 3.7
Classifier: Programming Language :: Python :: 3.8
Classifier: Programming Language :: Python :: 3.9
Classifier: Programming Language :: Python :: 3.10
Classifier: Topic :: Internet :: WWW/HTTP
License-File: LICENSE
Requires-Dist: requests (>=2.28.1)
Requires-Dist: tqdm (>=4.64.0)
Requires-Dist: urllib3 (>=1.26.11)
